odoo8_addon_sale_properties_dynamic_fields-8.0.1.0.0.99.dev29-py3.8-nspkg.pth
odoo_addons/sale_properties_dynamic_fields/README.rst
odoo_addons/sale_properties_dynamic_fields/__init__.py
odoo_addons/sale_properties_dynamic_fields/__openerp__.py
odoo_addons/sale_properties_dynamic_fields/mrp_property_group.py
odoo_addons/sale_properties_dynamic_fields/mrp_property_group_view.xml
odoo_addons/sale_properties_dynamic_fields/sale_order.py
odoo_addons/sale_properties_dynamic_fields/sale_order_line.py
odoo_addons/sale_properties_dynamic_fields/i18n/ca.po
odoo_addons/sale_properties_dynamic_fields/i18n/de.po
odoo_addons/sale_properties_dynamic_fields/i18n/es.po
odoo_addons/sale_properties_dynamic_fields/i18n/es_ES.po
odoo_addons/sale_properties_dynamic_fields/i18n/fi.po
odoo_addons/sale_properties_dynamic_fields/i18n/fr.po
odoo_addons/sale_properties_dynamic_fields/i18n/hr.po
odoo_addons/sale_properties_dynamic_fields/i18n/hu.po
odoo_addons/sale_properties_dynamic_fields/i18n/it.po
odoo_addons/sale_properties_dynamic_fields/i18n/nl.po
odoo_addons/sale_properties_dynamic_fields/i18n/nl_NL.po
odoo_addons/sale_properties_dynamic_fields/i18n/pt_BR.po
odoo_addons/sale_properties_dynamic_fields/i18n/ro.po
odoo_addons/sale_properties_dynamic_fields/i18n/ru.po
odoo_addons/sale_properties_dynamic_fields/i18n/sale_properties_dynamic_fields.pot
odoo_addons/sale_properties_dynamic_fields/i18n/sk.po
odoo_addons/sale_properties_dynamic_fields/i18n/sl.po
odoo_addons/sale_properties_dynamic_fields/i18n/tr.po
odoo_addons/sale_properties_dynamic_fields/i18n/tr_TR.po
odoo_addons/sale_properties_dynamic_fields/i18n/zh_CN.po
odoo_addons/sale_properties_dynamic_fields/static/description/icon.png
odoo_addons/sale_properties_dynamic_fields/test/properties.yml
odoo8_addon_sale_properties_dynamic_fields-8.0.1.0.0.99.dev29.dist-info/METADATA
odoo8_addon_sale_properties_dynamic_fields-8.0.1.0.0.99.dev29.dist-info/WHEEL
odoo8_addon_sale_properties_dynamic_fields-8.0.1.0.0.99.dev29.dist-info/namespace_packages.txt
odoo8_addon_sale_properties_dynamic_fields-8.0.1.0.0.99.dev29.dist-info/top_level.txt
odoo8_addon_sale_properties_dynamic_fields-8.0.1.0.0.99.dev29.dist-info/RECORD
