Metadata-Version: 2.1
Name: odoo8-addon-sale-properties-dynamic-fields
Version: 8.0.1.0.0.99.dev29
Summary: Sale properties dynamic fields
Home-page: http://www.agilebg.com
Author: Agile Business Group, Odoo Community Association (OCA)
Author-email: support@odoo-community.org
License: AGPL-3
Platform: UNKNOWN
Classifier: Programming Language :: Python
Classifier: Framework :: Odoo
Classifier: Framework :: Odoo :: 8.0
Classifier: License :: OSI Approved :: GNU Affero General Public License v3
Requires-Python: ~=2.7
Requires-Dist: odoo8-addon-sale-properties-easy-creation
Requires-Dist: odoo (<9.0a,>=8.0a)
